{
  "applications": ["payroll"],
  "changelogDate": "20220610015646",
  "dto": "no",
  "embedded": false,
  "entityTableName": "position_arl",
  "fields": [
    {
      "fieldName": "riskClass",
      "fieldType": "Integer",
      "fieldValidateRules": ["required"]
    },
    {
      "fieldName": "positionCode",
      "fieldType": "String",
      "fieldValidateRules": ["required", "maxlength"],
      "fieldValidateRulesMaxlength": "10"
    },
    {
      "fieldName": "position",
      "fieldType": "String",
      "fieldValidateRules": ["required", "maxlength"],
      "fieldValidateRulesMaxlength": "100"
    }
  ],
  "fluentMethods": true,
  "jpaMetamodelFiltering": false,
  "name": "PositionArl",
  "pagination": "no",
  "readOnly": false,
  "relationships": [],
  "service": "no"
}
